secretSanta/__init__.py
secretSanta/email_utils.py
secretSanta/logging.py
secretSanta/party.py
secretSanta/requirements.txt
secretSanta/version.py
secretSanta/inputs/guests.json
secret_santa_email-0.0.1.dist-info/LICENSE
secret_santa_email-0.0.1.dist-info/METADATA
secret_santa_email-0.0.1.dist-info/WHEEL
secret_santa_email-0.0.1.dist-info/top_level.txt
secret_santa_email-0.0.1.dist-info/RECORD
