Metadata-Version: 2.1
Name: secret-santa-email
Version: 0.0.1
Summary: SecretSanta: a toolbox for organizing secret Santa by email
Home-page: https://github.com/malihass/SecretSanta
Author: Malik Hassanaly
License: BSD 3-Clause
Classifier: License :: OSI Approved :: BSD License
Classifier: Natural Language :: English
Classifier: Programming Language :: Python :: 3.9
Classifier: Programming Language :: Python :: 3.10
Classifier: Programming Language :: Python :: 3.11
Classifier: Programming Language :: Python :: 3.12
Requires-Python: >=3.9
License-File: LICENSE
Requires-Dist: prettyPlot
